setup.py
./nl/__init__.py
./nl/clps.py
./nl/conf.py
./nl/exceptions.py
./nl/kb.py
./nl/log.py
./nl/metanl.py
./nl/nltime.py
./nl/prop.py
./nl/rule.py
./nl/state.py
./nl/thing.py
./nl/utils.py
./nl/examples/__init__.py
./nl/examples/cms.py
./nl/examples/cms2.py
./nl/examples/cms3.py
./nl/examples/modality.py
./nl/examples/nouns.py
./nl/examples/people.py
./nl/examples/physics.py
./nl/examples/physics22.py
./nl/examples/trac.py
./nl/test/__init__.py
./nl/test/functional_test.py
nl.egg-info/PKG-INFO
nl.egg-info/SOURCES.txt
nl.egg-info/dependency_links.txt
nl.egg-info/not-zip-safe
nl.egg-info/requires.txt
nl.egg-info/top_level.txt