Metadata-Version: 1.0
Name: nl
Version: 0.102
Summary: A python library that provides a production system with an API modelled on the natural language
Home-page: http://http://enriquepablo.github.com/nlproject/
Author: Enrique Perez Arnaud
Author-email: enriquepablo@gmail.com
License: GPL
Platform: UNKNOWN
Classifier: Topic :: Scientific/Engineering :: Artificial Intelligence
Classifier: Programming Language :: Python
Classifier: Topic :: Software Development :: Libraries :: Python Modules
